cnbc/__init__.py
cnbc/api_wrapper.py
cnbc/endpoints.py
cnbc/exceptions.py
cnbc-1.0.0.dist-info/LICENSE
cnbc-1.0.0.dist-info/METADATA
cnbc-1.0.0.dist-info/WHEEL
cnbc-1.0.0.dist-info/top_level.txt
cnbc-1.0.0.dist-info/RECORD
