Metadata-Version: 2.1
Name: cnbc
Version: 1.0.0
Summary: A Python package that wraps CNBC API endpoints and returns financial data in JSON.
Home-page: https://github.com/AG3NTZ3R0/cnbc
Author: Brandon J. Lacy
Author-email: Z3R0@duck.com
Project-URL: Bug Tracker, https://github.com/AG3NTZ3R0/cnbc/issues
Classifier: Programming Language :: Python :: 3
Classifier: License :: OSI Approved :: GNU General Public License v3 (GPLv3)
Classifier: Operating System :: OS Independent
Requires-Python: >=3.12
License-File: LICENSE
Requires-Dist: requests
